logger_print/__init__.py
logger_print-0.1.dist-info/METADATA
logger_print-0.1.dist-info/WHEEL
logger_print-0.1.dist-info/top_level.txt
logger_print-0.1.dist-info/RECORD
