Metadata-Version: 2.1
Name: logger-print
Version: 0.1
Summary: A simple package to redirect print statements to loguru logger.
Author: glwhappen
Author-email: 1597721684@qq.com
Project-URL: Source Code, https://github.com/glwhappen/logger_print
Requires-Dist: loguru
